ya/__init__.py
ya-0.0.5.dist-info/licenses/LICENSE
ya-0.0.5.dist-info/METADATA
ya-0.0.5.dist-info/WHEEL
ya-0.0.5.dist-info/top_level.txt
ya-0.0.5.dist-info/RECORD
