Metadata-Version: 2.4
Name: ya
Version: 0.0.5
Summary: Make filters with the mongo language
Home-page: https://github.com/t-c-w/ya
Author: Thor Whalen
License: apache-2.0
Platform: any
License-File: LICENSE
Dynamic: license-file
